socialtextlytics/__init__.py
socialtextlytics/main.py
socialtextlytics/prompts.py
socialtextlytics-2025.12.21131030.dist-info/METADATA
socialtextlytics-2025.12.21131030.dist-info/WHEEL
socialtextlytics-2025.12.21131030.dist-info/top_level.txt
socialtextlytics-2025.12.21131030.dist-info/RECORD
