Metadata-Version: 2.4
Name: socialtextlytics
Version: 2025.12.21131030
Summary: A new package that analyzes social media post text to extract structured insights about audience engagement patterns, such as identifying common themes in highly liked content or predicting potential
Author-email: socialtextlytics <hi@eugene.plus>
License: MIT
Project-URL: Homepage, https://github.com/chigwell/socialtextlytics
Requires-Python: >=3.9
Requires-Dist: langchain-llm7>=0.0.0
Requires-Dist: llmatch-messages>=0.0.0
Requires-Dist: langchain-core>=0.3.0
